{"nodes": [{"id": "edge_ssr_app", "label": "edge-ssr-app.js", "file_type": "code", "source_file": "packages\\engine\\node_modules\\next\\dist\\esm\\build\\templates\\edge-ssr-app.js", "source_location": "L1"}, {"id": "edge_ssr_app_maybejsonparse", "label": "maybeJSONParse()", "file_type": "code", "source_file": "packages\\engine\\node_modules\\next\\dist\\esm\\build\\templates\\edge-ssr-app.js", "source_location": "L21"}, {"id": "edge_ssr_app_nhandler", "label": "nHandler()", "file_type": "code", "source_file": "packages\\engine\\node_modules\\next\\dist\\esm\\build\\templates\\edge-ssr-app.js", "source_location": "L62"}], "edges": [{"source": "edge_ssr_app", "target": "globals", "relation": "imports_from", "confidence": "EXTRACTED", "source_file": "packages\\engine\\node_modules\\next\\dist\\esm\\build\\templates\\edge-ssr-app.js", "source_location": "L2", "weight": 1.0}, {"source": "edge_ssr_app", "target": "adapter", "relation": "imports_from", "confidence": "EXTRACTED", "source_file": "packages\\engine\\node_modules\\next\\dist\\esm\\build\\templates\\edge-ssr-app.js", "source_location": "L3", "weight": 1.0}, {"source": "edge_ssr_app", "target": "render", "relation": "imports_from", "confidence": "EXTRACTED", "source_file": "packages\\engine\\node_modules\\next\\dist\\esm\\build\\templates\\edge-ssr-app.js", "source_location": "L4", "weight": 1.0}, {"source": "edge_ssr_app", "target": "incremental_cache", "relation": "imports_from", "confidence": "EXTRACTED", "source_file": "packages\\engine\\node_modules\\next\\dist\\esm\\build\\templates\\edge-ssr-app.js", "source_location": "L5", "weight": 1.0}, {"source": "edge_ssr_app", "target": "app_render", "relation": "imports_from", "confidence": "EXTRACTED", "source_file": "packages\\engine\\node_modules\\next\\dist\\esm\\build\\templates\\edge-ssr-app.js", "source_location": "L6", "weight": 1.0}, {"source": "edge_ssr_app", "target": "var_userland", "relation": "imports_from", "confidence": "EXTRACTED", "source_file": "packages\\engine\\node_modules\\next\\dist\\esm\\build\\templates\\edge-ssr-app.js", "source_location": "L7", "weight": 1.0}, {"source": "edge_ssr_app", "target": "page_types", "relation": "imports_from", "confidence": "EXTRACTED", "source_file": "packages\\engine\\node_modules\\next\\dist\\esm\\build\\templates\\edge-ssr-app.js", "source_location": "L8", "weight": 1.0}, {"source": "edge_ssr_app", "target": "encryption_utils", "relation": "imports_from", "confidence": "EXTRACTED", "source_file": "packages\\engine\\node_modules\\next\\dist\\esm\\build\\templates\\edge-ssr-app.js", "source_location": "L9", "weight": 1.0}, {"source": "edge_ssr_app", "target": "action_utils", "relation": "imports_from", "confidence": "EXTRACTED", "source_file": "packages\\engine\\node_modules\\next\\dist\\esm\\build\\templates\\edge-ssr-app.js", "source_location": "L10", "weight": 1.0}, {"source": "edge_ssr_app", "target": "edge_ssr_app_maybejsonparse", "relation": "contains", "confidence": "EXTRACTED", "source_file": "packages\\engine\\node_modules\\next\\dist\\esm\\build\\templates\\edge-ssr-app.js", "source_location": "L21", "weight": 1.0}, {"source": "edge_ssr_app", "target": "edge_ssr_app_nhandler", "relation": "contains", "confidence": "EXTRACTED", "source_file": "packages\\engine\\node_modules\\next\\dist\\esm\\build\\templates\\edge-ssr-app.js", "source_location": "L62", "weight": 1.0}]}