{"nodes": [{"id": "emscripten_utils", "label": "emscripten-utils.js", "file_type": "code", "source_file": "packages\\engine\\node_modules\\next\\dist\\esm\\server\\lib\\squoosh\\emscripten-utils.js", "source_location": "L1"}, {"id": "emscripten_utils_pathify", "label": "pathify()", "file_type": "code", "source_file": "packages\\engine\\node_modules\\next\\dist\\esm\\server\\lib\\squoosh\\emscripten-utils.js", "source_location": "L2"}, {"id": "emscripten_utils_instantiateemscriptenwasm", "label": "instantiateEmscriptenWasm()", "file_type": "code", "source_file": "packages\\engine\\node_modules\\next\\dist\\esm\\server\\lib\\squoosh\\emscripten-utils.js", "source_location": "L8"}], "edges": [{"source": "emscripten_utils", "target": "url", "relation": "imports_from", "confidence": "EXTRACTED", "source_file": "packages\\engine\\node_modules\\next\\dist\\esm\\server\\lib\\squoosh\\emscripten-utils.js", "source_location": "L1", "weight": 1.0}, {"source": "emscripten_utils", "target": "emscripten_utils_pathify", "relation": "contains", "confidence": "EXTRACTED", "source_file": "packages\\engine\\node_modules\\next\\dist\\esm\\server\\lib\\squoosh\\emscripten-utils.js", "source_location": "L2", "weight": 1.0}, {"source": "emscripten_utils", "target": "emscripten_utils_instantiateemscriptenwasm", "relation": "contains", "confidence": "EXTRACTED", "source_file": "packages\\engine\\node_modules\\next\\dist\\esm\\server\\lib\\squoosh\\emscripten-utils.js", "source_location": "L8", "weight": 1.0}]}