{"nodes": [{"id": "merge_configs", "label": "merge-configs.ts", "file_type": "code", "source_file": "packages\\ui\\node_modules\\tailwind-merge\\src\\lib\\merge-configs.ts", "source_location": "L1"}, {"id": "merge_configs_mergeconfigs", "label": "mergeConfigs()", "file_type": "code", "source_file": "packages\\ui\\node_modules\\tailwind-merge\\src\\lib\\merge-configs.ts", "source_location": "L7"}, {"id": "merge_configs_overrideproperty", "label": "overrideProperty()", "file_type": "code", "source_file": "packages\\ui\\node_modules\\tailwind-merge\\src\\lib\\merge-configs.ts", "source_location": "L40"}, {"id": "merge_configs_overrideconfigproperties", "label": "overrideConfigProperties()", "file_type": "code", "source_file": "packages\\ui\\node_modules\\tailwind-merge\\src\\lib\\merge-configs.ts", "source_location": "L50"}, {"id": "merge_configs_mergeconfigproperties", "label": "mergeConfigProperties()", "file_type": "code", "source_file": "packages\\ui\\node_modules\\tailwind-merge\\src\\lib\\merge-configs.ts", "source_location": "L61"}], "edges": [{"source": "merge_configs", "target": "types", "relation": "imports_from", "confidence": "EXTRACTED", "source_file": "packages\\ui\\node_modules\\tailwind-merge\\src\\lib\\merge-configs.ts", "source_location": "L1", "weight": 1.0}, {"source": "merge_configs", "target": "merge_configs_mergeconfigs", "relation": "contains", "confidence": "EXTRACTED", "source_file": "packages\\ui\\node_modules\\tailwind-merge\\src\\lib\\merge-configs.ts", "source_location": "L7", "weight": 1.0}, {"source": "merge_configs", "target": "merge_configs_overrideproperty", "relation": "contains", "confidence": "EXTRACTED", "source_file": "packages\\ui\\node_modules\\tailwind-merge\\src\\lib\\merge-configs.ts", "source_location": "L40", "weight": 1.0}, {"source": "merge_configs", "target": "merge_configs_overrideconfigproperties", "relation": "contains", "confidence": "EXTRACTED", "source_file": "packages\\ui\\node_modules\\tailwind-merge\\src\\lib\\merge-configs.ts", "source_location": "L50", "weight": 1.0}, {"source": "merge_configs", "target": "merge_configs_mergeconfigproperties", "relation": "contains", "confidence": "EXTRACTED", "source_file": "packages\\ui\\node_modules\\tailwind-merge\\src\\lib\\merge-configs.ts", "source_location": "L61", "weight": 1.0}, {"source": "merge_configs_mergeconfigs", "target": "merge_configs_overrideproperty", "relation": "calls", "confidence": "INFERRED", "source_file": "packages\\ui\\node_modules\\tailwind-merge\\src\\lib\\merge-configs.ts", "source_location": "L18", "weight": 0.8}, {"source": "merge_configs_mergeconfigs", "target": "merge_configs_overrideconfigproperties", "relation": "calls", "confidence": "INFERRED", "source_file": "packages\\ui\\node_modules\\tailwind-merge\\src\\lib\\merge-configs.ts", "source_location": "L24", "weight": 0.8}, {"source": "merge_configs_mergeconfigs", "target": "merge_configs_mergeconfigproperties", "relation": "calls", "confidence": "INFERRED", "source_file": "packages\\ui\\node_modules\\tailwind-merge\\src\\lib\\merge-configs.ts", "source_location": "L31", "weight": 0.8}, {"source": "merge_configs_overrideconfigproperties", "target": "merge_configs_overrideproperty", "relation": "calls", "confidence": "INFERRED", "source_file": "packages\\ui\\node_modules\\tailwind-merge\\src\\lib\\merge-configs.ts", "source_location": "L56", "weight": 0.8}]}