{"nodes": [{"id": "kitchen_availability_test", "label": "kitchen-availability.test.ts", "file_type": "code", "source_file": "packages\\engine\\src\\orchestrators\\kitchen-availability.test.ts", "source_location": "L1"}], "edges": [{"source": "kitchen_availability_test", "target": "vitest", "relation": "imports_from", "confidence": "EXTRACTED", "source_file": "packages\\engine\\src\\orchestrators\\kitchen-availability.test.ts", "source_location": "L1", "weight": 1.0}, {"source": "kitchen_availability_test", "target": "kitchen_availability", "relation": "imports_from", "confidence": "EXTRACTED", "source_file": "packages\\engine\\src\\orchestrators\\kitchen-availability.test.ts", "source_location": "L2", "weight": 1.0}]}