{"nodes": [{"id": "fetch", "label": "fetch.ts", "file_type": "code", "source_file": "packages\\engine\\node_modules\\@supabase\\supabase-js\\src\\lib\\fetch.ts", "source_location": "L1"}, {"id": "fetch_resolvefetch", "label": "resolveFetch()", "file_type": "code", "source_file": "packages\\engine\\node_modules\\@supabase\\supabase-js\\src\\lib\\fetch.ts", "source_location": "L3"}, {"id": "fetch_resolveheadersconstructor", "label": "resolveHeadersConstructor()", "file_type": "code", "source_file": "packages\\engine\\node_modules\\@supabase\\supabase-js\\src\\lib\\fetch.ts", "source_location": "L10"}, {"id": "fetch_fetchwithauth", "label": "fetchWithAuth()", "file_type": "code", "source_file": "packages\\engine\\node_modules\\@supabase\\supabase-js\\src\\lib\\fetch.ts", "source_location": "L14"}], "edges": [{"source": "fetch", "target": "fetch_resolvefetch", "relation": "contains", "confidence": "EXTRACTED", "source_file": "packages\\engine\\node_modules\\@supabase\\supabase-js\\src\\lib\\fetch.ts", "source_location": "L3", "weight": 1.0}, {"source": "fetch", "target": "fetch_resolveheadersconstructor", "relation": "contains", "confidence": "EXTRACTED", "source_file": "packages\\engine\\node_modules\\@supabase\\supabase-js\\src\\lib\\fetch.ts", "source_location": "L10", "weight": 1.0}, {"source": "fetch", "target": "fetch_fetchwithauth", "relation": "contains", "confidence": "EXTRACTED", "source_file": "packages\\engine\\node_modules\\@supabase\\supabase-js\\src\\lib\\fetch.ts", "source_location": "L14", "weight": 1.0}, {"source": "fetch_fetchwithauth", "target": "fetch_resolvefetch", "relation": "calls", "confidence": "INFERRED", "source_file": "packages\\engine\\node_modules\\@supabase\\supabase-js\\src\\lib\\fetch.ts", "source_location": "L19", "weight": 0.8}, {"source": "fetch_fetchwithauth", "target": "fetch_resolveheadersconstructor", "relation": "calls", "confidence": "INFERRED", "source_file": "packages\\engine\\node_modules\\@supabase\\supabase-js\\src\\lib\\fetch.ts", "source_location": "L20", "weight": 0.8}]}