{"nodes": [{"id": "risk_engine", "label": "risk.engine.ts", "file_type": "code", "source_file": "packages\\engine\\src\\orchestrators\\risk.engine.ts", "source_location": "L1"}, {"id": "risk_engine_normalizecurrency", "label": "normalizeCurrency()", "file_type": "code", "source_file": "packages\\engine\\src\\orchestrators\\risk.engine.ts", "source_location": "L42"}, {"id": "risk_engine_isallowedcurrency", "label": "isAllowedCurrency()", "file_type": "code", "source_file": "packages\\engine\\src\\orchestrators\\risk.engine.ts", "source_location": "L47"}, {"id": "risk_engine_finalizeresult", "label": "finalizeResult()", "file_type": "code", "source_file": "packages\\engine\\src\\orchestrators\\risk.engine.ts", "source_location": "L55"}, {"id": "risk_engine_evaluatecustomerrisk", "label": "evaluateCustomerRisk()", "file_type": "code", "source_file": "packages\\engine\\src\\orchestrators\\risk.engine.ts", "source_location": "L108"}, {"id": "risk_engine_evaluatepaymentrisk", "label": "evaluatePaymentRisk()", "file_type": "code", "source_file": "packages\\engine\\src\\orchestrators\\risk.engine.ts", "source_location": "L141"}, {"id": "risk_engine_evaluateorderrisk", "label": "evaluateOrderRisk()", "file_type": "code", "source_file": "packages\\engine\\src\\orchestrators\\risk.engine.ts", "source_location": "L183"}, {"id": "risk_engine_evaluatecheckoutrisk", "label": "evaluateCheckoutRisk()", "file_type": "code", "source_file": "packages\\engine\\src\\orchestrators\\risk.engine.ts", "source_location": "L241"}], "edges": [{"source": "risk_engine", "target": "risk_engine_normalizecurrency", "relation": "contains", "confidence": "EXTRACTED", "source_file": "packages\\engine\\src\\orchestrators\\risk.engine.ts", "source_location": "L42", "weight": 1.0}, {"source": "risk_engine", "target": "risk_engine_isallowedcurrency", "relation": "contains", "confidence": "EXTRACTED", "source_file": "packages\\engine\\src\\orchestrators\\risk.engine.ts", "source_location": "L47", "weight": 1.0}, {"source": "risk_engine", "target": "risk_engine_finalizeresult", "relation": "contains", "confidence": "EXTRACTED", "source_file": "packages\\engine\\src\\orchestrators\\risk.engine.ts", "source_location": "L55", "weight": 1.0}, {"source": "risk_engine", "target": "risk_engine_evaluatecustomerrisk", "relation": "contains", "confidence": "EXTRACTED", "source_file": "packages\\engine\\src\\orchestrators\\risk.engine.ts", "source_location": "L108", "weight": 1.0}, {"source": "risk_engine", "target": "risk_engine_evaluatepaymentrisk", "relation": "contains", "confidence": "EXTRACTED", "source_file": "packages\\engine\\src\\orchestrators\\risk.engine.ts", "source_location": "L141", "weight": 1.0}, {"source": "risk_engine", "target": "risk_engine_evaluateorderrisk", "relation": "contains", "confidence": "EXTRACTED", "source_file": "packages\\engine\\src\\orchestrators\\risk.engine.ts", "source_location": "L183", "weight": 1.0}, {"source": "risk_engine", "target": "risk_engine_evaluatecheckoutrisk", "relation": "contains", "confidence": "EXTRACTED", "source_file": "packages\\engine\\src\\orchestrators\\risk.engine.ts", "source_location": "L241", "weight": 1.0}, {"source": "risk_engine_evaluatecustomerrisk", "target": "risk_engine_finalizeresult", "relation": "calls", "confidence": "INFERRED", "source_file": "packages\\engine\\src\\orchestrators\\risk.engine.ts", "source_location": "L116", "weight": 0.8}, {"source": "risk_engine_evaluatepaymentrisk", "target": "risk_engine_normalizecurrency", "relation": "calls", "confidence": "INFERRED", "source_file": "packages\\engine\\src\\orchestrators\\risk.engine.ts", "source_location": "L148", "weight": 0.8}, {"source": "risk_engine_evaluatepaymentrisk", "target": "risk_engine_isallowedcurrency", "relation": "calls", "confidence": "INFERRED", "source_file": "packages\\engine\\src\\orchestrators\\risk.engine.ts", "source_location": "L153", "weight": 0.8}, {"source": "risk_engine_evaluatepaymentrisk", "target": "risk_engine_finalizeresult", "relation": "calls", "confidence": "INFERRED", "source_file": "packages\\engine\\src\\orchestrators\\risk.engine.ts", "source_location": "L163", "weight": 0.8}, {"source": "risk_engine_evaluateorderrisk", "target": "risk_engine_evaluatepaymentrisk", "relation": "calls", "confidence": "INFERRED", "source_file": "packages\\engine\\src\\orchestrators\\risk.engine.ts", "source_location": "L198", "weight": 0.8}, {"source": "risk_engine_evaluateorderrisk", "target": "risk_engine_normalizecurrency", "relation": "calls", "confidence": "INFERRED", "source_file": "packages\\engine\\src\\orchestrators\\risk.engine.ts", "source_location": "L216", "weight": 0.8}, {"source": "risk_engine_evaluateorderrisk", "target": "risk_engine_isallowedcurrency", "relation": "calls", "confidence": "INFERRED", "source_file": "packages\\engine\\src\\orchestrators\\risk.engine.ts", "source_location": "L217", "weight": 0.8}, {"source": "risk_engine_evaluateorderrisk", "target": "risk_engine_finalizeresult", "relation": "calls", "confidence": "INFERRED", "source_file": "packages\\engine\\src\\orchestrators\\risk.engine.ts", "source_location": "L222", "weight": 0.8}, {"source": "risk_engine_evaluatecheckoutrisk", "target": "risk_engine_evaluatecustomerrisk", "relation": "calls", "confidence": "INFERRED", "source_file": "packages\\engine\\src\\orchestrators\\risk.engine.ts", "source_location": "L249", "weight": 0.8}, {"source": "risk_engine_evaluatecheckoutrisk", "target": "risk_engine_evaluatepaymentrisk", "relation": "calls", "confidence": "INFERRED", "source_file": "packages\\engine\\src\\orchestrators\\risk.engine.ts", "source_location": "L260", "weight": 0.8}, {"source": "risk_engine_evaluatecheckoutrisk", "target": "risk_engine_finalizeresult", "relation": "calls", "confidence": "INFERRED", "source_file": "packages\\engine\\src\\orchestrators\\risk.engine.ts", "source_location": "L287", "weight": 0.8}]}